libr/__init__.py
libr/r_anal.py
libr/r_asm.py
libr/r_bin.py
libr/r_bp.py
libr/r_config.py
libr/r_cons.py
libr/r_core.py
libr/r_crypto.py
libr/r_debug.py
libr/r_egg.py
libr/r_flag.py
libr/r_fs.py
libr/r_hash.py
libr/r_io.py
libr/r_lang.py
libr/r_libs.py
libr/r_magic.py
libr/r_main.py
libr/r_parse.py
libr/r_reg.py
libr/r_search.py
libr/r_socket.py
libr/r_syscall.py
libr/r_util.py
libr/libr/libr_anal.5.7.4.dylib
libr/libr/libr_anal.dylib
libr/libr/libr_asm.5.7.4.dylib
libr/libr/libr_asm.dylib
libr/libr/libr_bin.5.7.4.dylib
libr/libr/libr_bin.dylib
libr/libr/libr_bp.5.7.4.dylib
libr/libr/libr_bp.dylib
libr/libr/libr_config.5.7.4.dylib
libr/libr/libr_config.dylib
libr/libr/libr_cons.5.7.4.dylib
libr/libr/libr_cons.dylib
libr/libr/libr_core.5.7.4.dylib
libr/libr/libr_core.dylib
libr/libr/libr_crypto.5.7.4.dylib
libr/libr/libr_crypto.dylib
libr/libr/libr_debug.5.7.4.dylib
libr/libr/libr_debug.dylib
libr/libr/libr_egg.5.7.4.dylib
libr/libr/libr_egg.dylib
libr/libr/libr_flag.5.7.4.dylib
libr/libr/libr_flag.dylib
libr/libr/libr_fs.5.7.4.dylib
libr/libr/libr_fs.dylib
libr/libr/libr_hash.5.7.4.dylib
libr/libr/libr_hash.dylib
libr/libr/libr_io.5.7.4.dylib
libr/libr/libr_io.dylib
libr/libr/libr_lang.5.7.4.dylib
libr/libr/libr_lang.dylib
libr/libr/libr_magic.5.7.4.dylib
libr/libr/libr_magic.dylib
libr/libr/libr_main.5.7.4.dylib
libr/libr/libr_main.dylib
libr/libr/libr_parse.5.7.4.dylib
libr/libr/libr_parse.dylib
libr/libr/libr_reg.5.7.4.dylib
libr/libr/libr_reg.dylib
libr/libr/libr_search.5.7.4.dylib
libr/libr/libr_search.dylib
libr/libr/libr_socket.5.7.4.dylib
libr/libr/libr_socket.dylib
libr/libr/libr_syscall.5.7.4.dylib
libr/libr/libr_syscall.dylib
libr/libr/libr_util.5.7.4.dylib
libr/libr/libr_util.dylib
r2libr-5.7.4.dist-info/LICENSE
r2libr-5.7.4.dist-info/METADATA
r2libr-5.7.4.dist-info/WHEEL
r2libr-5.7.4.dist-info/top_level.txt
r2libr-5.7.4.dist-info/RECORD
