Metadata-Version: 2.1
Name: r2libr
Version: 5.7.4
Summary: Yet anohter radare2 python bindings.
Home-page: https://github.com/radareorg/radare2-bindings/tree/master/r2libr
Author: mio
Author-email: mio@lazym.io
License: UNKNOWN
Platform: UNKNOWN
Classifier: Programming Language :: Python :: 3
Requires-Python: >=3.6
License-File: LICENSE
